test_gen_framework/__init__.py
test_gen_framework/ci.yml
test_gen_framework/config.py
test_gen_framework/post_install.py
test_gen_framework/cli/cli.py
test_gen_framework/cli/commands/execute.py
test_gen_framework/cli/commands/generate.py
test_gen_framework/execution/Test_analysis.py
test_gen_framework/execution/Test_execution.py
test_gen_framework/generation/AI_Client.py
test_gen_framework/generation/Test_generation.py
test_gen_framework/prioritization/test_prioritizer.py
test_gen_framework/reporting/Test_report.py
test_gen_framework/services/Dashboard_service.py
test_gen_framework/services/Github_service.py
test_gen_framework/services/LLM_service.py
test_gen_framework/storage/test_metadata.json
test_gen_framework-1.0.8.dist-info/licenses/LICENSE
test_gen_framework-1.0.8.dist-info/METADATA
test_gen_framework-1.0.8.dist-info/WHEEL
test_gen_framework-1.0.8.dist-info/entry_points.txt
test_gen_framework-1.0.8.dist-info/top_level.txt
test_gen_framework-1.0.8.dist-info/RECORD
