Metadata-Version: 2.4
Name: test_gen_framework
Version: 1.0.8
Summary: Test Generation Framework
License: MIT
License-File: LICENSE
Requires-Dist: requests
Requires-Dist: pytest
Requires-Dist: PyYAML
Requires-Dist: gitpython
Requires-Dist: pygithub
Requires-Dist: pytest-json
Requires-Dist: pytest-json-report
Requires-Dist: coverage
Dynamic: license-file
